{
  "data": {
    "breakBlockSound": {
      "volume": {
        "value": 0
      }
    },
    "dropSelf": {
      "canDropSelf": false
    },
    "name": {
      "value": "block_concrete_powder_lime"
    },
    "placeBlockSound": {
      "volume": {
        "value": 0
      }
    },
    "textures": {
      "back": {
        "asset": "asset/Texture/Block/concrete_powder_lime.png"
      },
      "down": {
        "asset": "asset/Texture/Block/concrete_powder_lime.png"
      },
      "front": {
        "asset": "asset/Texture/Block/concrete_powder_lime.png"
      },
      "left": {
        "asset": "asset/Texture/Block/concrete_powder_lime.png"
      },
      "right": {
        "asset": "asset/Texture/Block/concrete_powder_lime.png"
      },
      "up": {
        "asset": "asset/Texture/Block/concrete_powder_lime.png"
      }
    }
  },
  "meta": {
    "EXPORT": {
      "setting.json": "cb287863308be2f777cc76e5ebd66642",
      "triggers.bts": ""
    },
    "VERSION": "0.23"
  }
}